Pre/课上/pre/remake/recognition.v
`define S0 2'b00 //reset
`define S1 2'b01 //1
`define S2 2'b10 //10
`define S3 2'b11 //101
module recognition(
    input clk,
    input reset,
    input in,
    output out 
);
    reg [1:0]state;
    reg [1:0]next;
    initial begin //初始化
        state=`S0;
        next=`S0;
    end
    always@(*)begin //状态转移,最好用assign驱动不写always *
        case(state)
        `S0:
            if(in==1)
                next=`S1;
            else
                next=`S0;
        `S1://1
            if(in==1)
                next=`S1;
            else
                next=`S2;
        `S2://10
            if(in==1)
                next=`S3;
            else
                next=`S0;
        `S3://101
            if(in==1)
                next=`S1;
            else
                next=`S2;

        endcase
    end
  always @(posedge clk,posedge reset) begin //状态存储
        if(reset==1)begin
            state=`S0;
            next=`S0;
        end
        else begin
        state=next;
        end
  end
    assign out=((state==`S2)&&(in==1))?1:0;//输出和当前状态以及输入有关
endmodule

Pre/课上/pre/remake/tb.v
`timescale  1ns / 1ps    
`include "recognition.v"
module tb_recognition;   

reg   clk                                  = 0 ;
reg   reset                                = 0 ;
reg   in                                   = 0 ;
wire  out                                  ;

recognition  u_recognition (
    .clk                     ( clk     ),
    .reset                   ( reset   ),
    .in                      ( in      ),

    .out                     ( out     )
);

initial
begin
    $dumpfile("wave.vcd");
	$dumpvars;
    clk=0;
    reset=1;
    in = 0;
    #2 reset=0;
    #2 in=1;
    #2 in=0;
    #2 in=1;
    #2 in=0;
    #2 in=1;
    #10
    $finish;
end
always #1 clk=~clk;
endmodule

Pre/课上/pre/remake/wave.vcd
$date
	Tue Sep 27 23:13:59 2022
$end
$version
	Icarus Verilog
$end
$timescale
	1ps
$end
$scope module tb_recognition $end
$var wire 1 ! out $end
$var reg 1 " clk $end
$var reg 1 # in $end
$var reg 1 $ reset $end
$scope module u_recognition $end
$var wire 1 " clk $end
$var wire 1 # in $end
$var wire 1 $ reset $end
$var wire 1 ! out $end
$var reg 2 % next [1:0] $end
$var reg 2 & state [1:0] $end
$upscope $end
$upscope $end
$enddefinitions $end
#0
$dumpvars
b0 &
b10 %
1$
0#
0"
0!
$end
#1000
b0 %
b10 &
1"
#2000
0"
0$
#3000
b10 %
b0 &
1"
#4000
b1 %
0"
1#
#5000
b1 &
1"
#6000
b10 %
0"
0#
#7000
b0 %
b10 &
1"
#8000
1!
b11 %
0"
1#
#9000
0!
b1 %
b11 &
1"
#10000
b10 %
0"
0#
#11000
b0 %
b10 &
1"
#12000
1!
b11 %
0"
1#
#13000
0!
b1 %
b11 &
1"
#14000
0"
#15000
b1 &
1"
