Pre/ISE-verilog/CPU_check/cpu_checker.v
`define S0 4'd0
`define S1 4'd1
`define S2 4'd2
`define S3 4'd3
`define S4 4'd4
`define S5 4'd5
`define S6 4'd6
`define S7 4'd7
`define S8 4'd8
`define S9 4'd9
`define S10 4'd10
`define S11 4'd11

module cpu_checker(
    input clk,
    input reset,
    input [7:0] char,
    output [1:0] format_type
  );
  reg [3:0] state;
  integer dexcnt=0;//十进制数字计数
  integer hexcnt=0;//16进制计数
  integer spacecnt=0;
  integer flag;//用来标记是哪一种，0是寄存器信息，1是数据存储器信息
  initial
  begin
    state=`S0;
  end
  always @(posedge clk)
  begin
    if(reset==1)
    begin
      state=`S0;
      spacecnt=0;
      hexcnt=0;
      dexcnt=0;
    end
    else
    begin
      case(state)
        `S0:
        begin//^
          if(char=="^")//^
            state=`S1;
        end
        `S1:
        begin//^XXXX
          if(char>=8'd48&&char<=8'd57)
          begin
            dexcnt=dexcnt+1;
            if(dexcnt>4)
            begin
              state=`S0;
              dexcnt=0;
            end
          end
          else if(char==8'd64)
          begin
            if(dexcnt>=1&&dexcnt<=4)
            begin
              state=`S2;
              dexcnt=0;
            end
          end
          else if(char==8'd94)
          begin
            dexcnt=0;
            state=`S1;
          end
          else
          begin
            state=`S0;
            dexcnt=0;
          end
        end
        `S2:
        begin//^xxxx@
          if (char>=8'd48&&char<=8'd57||char>=8'd97&&char<=8'd102)
          begin
            hexcnt=hexcnt+1;
            if(hexcnt>8)
            begin
              hexcnt=0;
              state=`S0;
            end
          end
          else if(char==":")
          begin
            if(hexcnt==8)
            begin
              hexcnt=0;
              state=`S3;
            end
            else
            begin
              hexcnt=0;
              state=`S0;
            end
          end
          else if(char=="^")
          begin
            hexcnt=0;
            state=`S1;
          end
           else begin
             hexcnt=0;
             state=`S0;
           end
        end
        `S3:
        begin//^xxxx@xxxxxxxx:
          if(char=="$"||char=="*")
          begin
            if(char=="$")
              flag=0;
            else
              flag=1;
            state=`S4;
          end
          else if(char==" ")
            state=`S3;
          else if(char=="^")
            state=`S1;
          else
          begin
            state=`S0;
          end
        end
        `S4:
        begin//^xxxx@xxxxxxxx:$(*)
          if(flag==0)
          begin
            if(char>=8'd48&&char<=8'd57&&spacecnt==0)
            begin
              dexcnt=dexcnt+1;
              if(dexcnt>4)
              begin
                state=`S0;
                dexcnt=0;
              end
            end
            else if(char==" ")
            begin
              if(dexcnt>=1&&dexcnt<=4)
              begin
                spacecnt=spacecnt+1;
                state=`S4;
              end
              else
              begin
                spacecnt=0;
                dexcnt=0;
                state=`S0;
              end
            end
            else if(char=="<"&&dexcnt>=1&&dexcnt<=4)
            begin
              dexcnt=0;
              spacecnt=0;
              state=`S5;
            end
            else if(char=="^")
            begin
              dexcnt=0;
              spacecnt=0;
              state=`S1;
            end
            else
            begin
              dexcnt=0;
              spacecnt=0;
              state=`S0;
            end
          end
          else
          begin
            if((char>=8'd48&&char<=8'd57||char>=8'd97&&char<=8'd102)&&spacecnt==0)
            begin
              hexcnt=hexcnt+1;
              if (hexcnt>8)
              begin
                hexcnt=0;
                spacecnt=0;
                state=`S0;
              end
            end
            else if(hexcnt==8&&char==" ")
            begin
              spacecnt=spacecnt+1;
              state=`S4;
            end
            else if(hexcnt==8&&char=="<")
            begin
              state=`S5;
              spacecnt=0;
              hexcnt=0;
            end
            else if(char=="^")
            begin
              spacecnt=0;
              hexcnt=0;
              state=`S1;
            end
            else
            begin
              spacecnt=0;
              hexcnt=0;
              state=`S0;
            end
          end
        end
        `S5:
        begin////^xxxx@xxxxxxxx:$(*)xxx<=
          if(char=="=")
          begin
            state=`S6;
          end
          else if(char=="^")
          begin
            state=`S1;
          end
          else
            state=`S0;
        end
        `S6:
        begin
          if(char==" "&&hexcnt==0)
          begin
            spacecnt=spacecnt+1;
            state=`S6;
          end
          else if(char>=8'd48&&char<=8'd57||char>=8'd97&&char<=8'd102)
          begin
            hexcnt=hexcnt+1;
            if (hexcnt>8)
            begin
              hexcnt=0;
              spacecnt=0;
              state=`S0;
            end
          end
          else if(char=="#")
          begin
            if(hexcnt==8)
            begin
              state=`S7;
              hexcnt=0;
              spacecnt=0;
            end
            else
            begin
              state=`S0;
              hexcnt=0;
              spacecnt=0;
            end
          end
          else if(char=="^")
          begin
            state=`S1;
            hexcnt=0;
            spacecnt=0;
          end
          else
          begin
            state=`S0;
            hexcnt=0;
            spacecnt=0;
          end
        end
        `S7:
        begin
          if(char=="^")
            state=`S1;
          else
            state=`S0;
        end
      endcase
    end
  end
  assign format_type=(state==`S7&&flag==0)?2'b01:(state==`S7&&flag==1)?2'b10:2'b00;
endmodule

Pre/ISE-verilog/CPU_check/cpu_check_tb.v
`timescale 1ns / 1ps
`include "cpu_checker.v"
module cpu_checker_tb;

	// Inputs
	reg clk;
	reg reset;
	reg [7:0] char;
	reg [15:0] freq;
	reg finish;

	// Outputs
	wire [1:0] format_type;
	wire [3:0] error_code;
	integer out;
   always @(posedge clk) begin
      if (!reset && !finish) begin
         $display("%d", format_type);
		$fwrite(out,"%d\n", format_type);
      end
   end

	// Instantiate the Unit Under Test (UUT)
	cpu_checker uut(
		.clk(clk),
		.reset(reset),
		.char(char),
		.format_type(format_type)
	);

	initial begin
		// Initialize Inputs
		$dumpfile("cpu_checker_wave1.vcd");
		$dumpvars;
		out=$fopen("out.txt","w");
		clk = 0;
		reset = 1;
		char = 0;
		freq = 2;
		finish = 0;

		#10 reset = 0;
#2 char = "2";
#2 char = "4";
#2 char = "2";
#2 char = "@";
#2 char = "0";
#2 char = "0";
#2 char = "0";
#2 char = "0";
#2 char = "3";
#2 char = "0";
#2 char = "f";
#2 char = "4";
#2 char = ":";
#2 char = " ";
#2 char = "$";
#2 char = "3";
#2 char = "1";
#2 char = " ";
#2 char = "<";
#2 char = "=";
#2 char = "1";
#2 char = "2";
#2 char = "3";
#2 char = "4";
#2 char = "5";
#2 char = "6";
#2 char = "7";
#2 char = "8";
#2 char = "#";
#2 char = "^";
#2 char = "2";
#2 char = "4";
#2 char = "2";
#2 char = "@";
#2 char = "0";
#2 char = "0";
#2 char = "0";
#2 char = "0";
#2 char = "3";
#2 char = "0";
#2 char = "f";
#2 char = "4";
#2 char = ":";
#2 char = " ";
#2 char = "$";
#2 char = "3";
#2 char = "1";
#2 char = " ";
#2 char = "<";
#2 char = "=";
#2 char = "1";
#2 char = "2";
#2 char = "3";
#2 char = "2";
#2 char = "1";
#2 char = "5";
#2 char = "#";
#2 char = "^";
#2 char = "2";
#2 char = "4";
#2 char = "2";
#2 char = "@";
#2 char = "0";
#2 char = "0";
#2 char = "0";
#2 char = "0";
#2 char = "3";
#2 char = "0";
#2 char = "f";
#2 char = "4";
#2 char = ":";
#2 char = " ";
#2 char = "$";
#2 char = "3";
#2 char = "1";
#2 char = " ";
#2 char = "<";
#2 char = "=";
#2 char = "1";
#2 char = "2";
#2 char = "3";
#2 char = "2";
#2 char = "1";
#2 char = "5";
#2 char = "8";
#2 char = "9";
#2 char = "9";
#2 char = "8";
#2 char = "#";
#2 char = "^";
#2 char = "2";
#2 char = "4";
#2 char = "2";
#2 char = "@";
#2 char = "0";
#2 char = "0";
#2 char = "0";
#2 char = "0";
#2 char = "3";
#2 char = "0";
#2 char = "f";
#2 char = "4";
#2 char = ":";
#2 char = " ";
#2 char = "$";
#2 char = "3";
#2 char = "1";
#2 char = " ";
#2 char = "<";
#2 char = "=";
#2 char = "#";
#2 char = "^";
#2 char = "2";
#2 char = "4";
#2 char = "2";
#2 char = "@";
#2 char = "0";
#2 char = "0";
#2 char = "0";
#2 char = "0";
#2 char = "3";
#2 char = "0";
#2 char = "f";
#2 char = "4";
#2 char = ":";
#2 char = " ";
#2 char = "$";
#2 char = "3";
#2 char = "1";
#2 char = " ";
#2 char = "<";
#2 char = "=";
#2 char = " ";
#2 char = " ";
#2 char = " ";
#2 char = "1";
#2 char = "2";
#2 char = "3";
#2 char = "2";
#2 char = "1";
#2 char = "5";
#2 char = " ";
#2 char = "#";
#2 char = "^";
#2 char = "2";
#2 char = "4";
#2 char = "2";
#2 char = "@";
#2 char = "0";
#2 char = "0";
#2 char = "0";
#2 char = "0";
#2 char = "3";
#2 char = "0";
#2 char = "f";
#2 char = "4";
#2 char = ":";
#2 char = " ";
#2 char = "$";
#2 char = "3";
#2 char = "1";
#2 char = " ";
#2 char = "<";
#2 char = "=";
#2 char = " ";
#2 char = " ";
#2 char = " ";
#2 char = "a";
#2 char = "b";
#2 char = "1";
#2 char = "2";
#2 char = "3";
#2 char = "2";
#2 char = "1";
#2 char = "5";
#2 char = " ";
#2 char = "#";
#2 char = "^";
#2 char = "2";
#2 char = "4";
#2 char = "2";
#2 char = "@";
#2 char = "0";
#2 char = "0";
#2 char = "0";
#2 char = "0";
#2 char = "3";
#2 char = "0";
#2 char = "f";
#2 char = "4";
#2 char = ":";
#2 char = " ";
#2 char = "$";
#2 char = "3";
#2 char = "1";
#2 char = " ";
#2 char = "<";
#2 char = "=";
#2 char = " ";
#2 char = " ";
#2 char = " ";
#2 char = "A";
#2 char = "b";
#2 char = "1";
#2 char = "2";
#2 char = "3";
#2 char = "2";
#2 char = "1";
#2 char = "5";
#2 char = " ";
#2 char = "#";
#2 char = "^";
#2 char = "3";
#2 char = "3";
#2 char = "8";
#2 char = "@";
#2 char = "0";
#2 char = "0";
#2 char = "0";
#2 char = "0";
#2 char = "3";
#2 char = "1";
#2 char = "3";
#2 char = "0";
#2 char = ":";
#2 char = " ";
#2 char = "*";
#2 char = "0";
#2 char = "0";
#2 char = "0";
#2 char = "0";
#2 char = "0";
#2 char = "0";
#2 char = "8";
#2 char = "8";
#2 char = " ";
#2 char = "<";
#2 char = "=";
#2 char = " ";
#2 char = "F";
#2 char = "f";
#2 char = "f";
#2 char = "f";
#2 char = "b";
#2 char = "5";
#2 char = "2";
#2 char = "8";
#2 char = "#";
#2 char = "^";
#2 char = "3";
#2 char = "3";
#2 char = "8";
#2 char = "@";
#2 char = "0";
#2 char = "0";
#2 char = "0";
#2 char = "0";
#2 char = "3";
#2 char = "1";
#2 char = "3";
#2 char = "0";
#2 char = ":";
#2 char = " ";
#2 char = "*";
#2 char = "0";
#2 char = "0";
#2 char = "0";
#2 char = "0";
#2 char = "0";
#2 char = "0";
#2 char = "8";
#2 char = "8";
#2 char = " ";
#2 char = "<";
#2 char = "=";
#2 char = " ";
#2 char = "f";
#2 char = "f";
#2 char = "f";
#2 char = "f";
#2 char = "b";
#2 char = "5";
#2 char = "2";
#2 char = "8";
#2 char = "#";
#2 char = "^";
#2 char = "3";
#2 char = "3";
#2 char = "8";
#2 char = "@";
#2 char = "0";
#2 char = "0";
#2 char = "0";
#2 char = "0";
#2 char = "3";
#2 char = "1";
#2 char = "3";
#2 char = "0";
#2 char = ":";
#2 char = " ";
#2 char = "*";
#2 char = "0";
#2 char = "0";
#2 char = "0";
#2 char = "0";
#2 char = "0";
#2 char = "0";
#2 char = "8";
#2 char = "8";
#2 char = " ";
#2 char = "<";
#2 char = "=";
#2 char = "#";
#2 char = "^";
#2 char = "3";
#2 char = "3";
#2 char = "8";
#2 char = "@";
#2 char = "0";
#2 char = "0";
#2 char = "0";
#2 char = "0";
#2 char = "3";
#2 char = "1";
#2 char = "3";
#2 char = "0";
#2 char = ":";
#2 char = " ";
#2 char = "*";
#2 char = "0";
#2 char = "0";
#2 char = "0";
#2 char = "0";
#2 char = "0";
#2 char = "0";
#2 char = "8";
#2 char = "8";
#2 char = " ";
#2 char = "<";
#2 char = "=";
#2 char = " ";
#2 char = "f";
#2 char = "f";
#2 char = "f";
#2 char = "f";
#2 char = "b";
#2 char = "5";
#2 char = "2";
#2 char = "8";
#2 char = "1";
#2 char = "2";
#2 char = "#";
#2 char = "^";
#2 char = "3";
#2 char = "3";
#2 char = "8";
#2 char = "@";
#2 char = "0";
#2 char = "0";
#2 char = "0";
#2 char = "0";
#2 char = "3";
#2 char = "1";
#2 char = "3";
#2 char = "0";
#2 char = ":";
#2 char = " ";
#2 char = "*";
#2 char = "0";
#2 char = "0";
#2 char = "0";
#2 char = "0";
#2 char = "0";
#2 char = "0";
#2 char = "8";
#2 char = "8";
#2 char = " ";
#2 char = "<";
#2 char = "=";
#2 char = " ";
#2 char = "f";
#2 char = "f";
#2 char = "f";
#2 char = "f";
#2 char = "b";
#2 char = "5";
#2 char = "2";
#2 char = "#";
#2 char = "^";
#2 char = "3";
#2 char = "3";
#2 char = "8";
#2 char = "@";
#2 char = "0";
#2 char = "0";
#2 char = "0";
#2 char = "0";
#2 char = "3";
#2 char = "1";
#2 char = "3";
#2 char = "0";
#2 char = ":";
#2 char = " ";
#2 char = "*";
#2 char = "0";
#2 char = "0";
#2 char = "0";
#2 char = "0";
#2 char = "0";
#2 char = "0";
#2 char = "8";
#2 char = "8";
#2 char = " ";
#2 char = "<";
#2 char = "=";
#2 char = " ";
#2 char = "f";
#2 char = "f";
#2 char = "f";
#2 char = "f";
#2 char = "B";
#2 char = "5";
#2 char = "2";
#2 char = "8";
#2 char = "#";
#2 char = "^";
#2 char = "3";
#2 char = "3";
#2 char = "8";
#2 char = "@";
#2 char = "0";
#2 char = "0";
#2 char = "0";
#2 char = "0";
#2 char = "3";
#2 char = "1";
#2 char = "3";
#2 char = "0";
#2 char = ":";
#2 char = " ";
#2 char = "*";
#2 char = "0";
#2 char = "0";
#2 char = "0";
#2 char = "0";
#2 char = "0";
#2 char = "0";
#2 char = "8";
#2 char = "8";
#2 char = " ";
#2 char = "<";
#2 char = "=";
#2 char = " ";
#2 char = "f";
#2 char = "f";
#2 char = "f";
#2 char = "f";
#2 char = "b";
#2 char = "5";
#2 char = "2";
#2 char = "B";
#2 char = "#";
#2 char = "^";
#2 char = "3";
#2 char = "3";
#2 char = "8";
#2 char = "@";
#2 char = "0";
#2 char = "0";
#2 char = "0";
#2 char = "0";
#2 char = "3";
#2 char = "1";
#2 char = "3";
#2 char = "0";
#2 char = ":";
#2 char = " ";
#2 char = "*";
#2 char = "0";
#2 char = "0";
#2 char = "0";
#2 char = "0";
#2 char = "0";
#2 char = "0";
#2 char = "8";
#2 char = "8";
#2 char = " ";
#2 char = "<";
#2 char = "=";
#2 char = " ";
#2 char = "f";
#2 char = "f";
#2 char = "f";
#2 char = "f";
#2 char = "b";
#2 char = "5";
#2 char = "2";
#2 char = "B";
#2 char = "#";
#2 char = "^";
#2 char = "3";
#2 char = "3";
#2 char = "8";
#2 char = "@";
#2 char = "0";
#2 char = "0";
#2 char = "0";
#2 char = "0";
#2 char = "3";
#2 char = "1";
#2 char = "3";
#2 char = "0";
#2 char = ":";
#2 char = " ";
#2 char = "*";
#2 char = "0";
#2 char = "0";
#2 char = "0";
#2 char = "0";
#2 char = "0";
#2 char = "0";
#2 char = "8";
#2 char = "8";
#2 char = " ";
#2 char = "<";
#2 char = "=";
#2 char = " ";
#2 char = "f";
#2 char = "f";
#2 char = "f";
#2 char = "f";
#2 char = "b";
#2 char = "5";
#2 char = "2";
#2 char = "B";
#2 char = " ";
#2 char = "#";
		#20
		finish = 1;
		$finish;
		
	end

    always #1 clk = ~clk;

endmodule

Pre/ISE-verilog/CPU_check/cpu_checker_wave1.vcd
$date
	Thu Aug 25 09:29:50 2022
$end
$version
	Icarus Verilog
$end
$timescale
	1ps
$end
$scope module cpu_checker_tb $end
$var wire 2 ! format_type [1:0] $end
$var reg 8 " char [7:0] $end
$var reg 1 # clk $end
$var reg 1 $ finish $end
$var reg 16 % freq [15:0] $end
$var reg 1 & reset $end
$var integer 32 ' out [31:0] $end
$scope module uut $end
$var wire 8 ( char [7:0] $end
$var wire 1 # clk $end
$var wire 1 & reset $end
$var wire 2 ) format_type [1:0] $end
$var reg 4 * state [3:0] $end
$var integer 32 + dexcnt [31:0] $end
$var integer 32 , flag [31:0] $end
$var integer 32 - hexcnt [31:0] $end
$var integer 32 . spacecnt [31:0] $end
$upscope $end
$upscope $end
$enddefinitions $end
#0
$dumpvars
b0 .
b0 -
bx ,
b0 +
b0 *
b0 )
b0 (
b10000000000000000000000000000011 '
1&
b10 %
0$
0#
b0 "
b0 !
$end
#1000
1#
#2000
0#
#3000
1#
#4000
0#
#5000
1#
#6000
0#
#7000
1#
#8000
0#
#9000
1#
#10000
0#
0&
#11000
1#
#12000
0#
b110010 "
b110010 (
#13000
1#
#14000
0#
b110100 "
b110100 (
#15000
1#
#16000
0#
b110010 "
b110010 (
#17000
1#
#18000
0#
b1000000 "
b1000000 (
#19000
1#
#20000
0#
b110000 "
b110000 (
#21000
1#
#22000
0#
#23000
1#
#24000
0#
#25000
1#
#26000
0#
#27000
1#
#28000
0#
b110011 "
b110011 (
#29000
1#
#30000
0#
b110000 "
b110000 (
#31000
1#
#32000
0#
b1100110 "
b1100110 (
#33000
1#
#34000
0#
b110100 "
b110100 (
#35000
1#
#36000
0#
b111010 "
b111010 (
#37000
1#
#38000
0#
b100000 "
b100000 (
#39000
1#
#40000
0#
b100100 "
b100100 (
#41000
1#
#42000
0#
b110011 "
b110011 (
#43000
1#
#44000
0#
b110001 "
b110001 (
#45000
1#
#46000
0#
b100000 "
b100000 (
#47000
1#
#48000
0#
b111100 "
b111100 (
#49000
1#
#50000
0#
b111101 "
b111101 (
#51000
1#
#52000
0#
b110001 "
b110001 (
#53000
1#
#54000
0#
b110010 "
b110010 (
#55000
1#
#56000
0#
b110011 "
b110011 (
#57000
1#
#58000
0#
b110100 "
b110100 (
#59000
1#
#60000
0#
b110101 "
b110101 (
#61000
1#
#62000
0#
b110110 "
b110110 (
#63000
1#
#64000
0#
b110111 "
b110111 (
#65000
1#
#66000
0#
b111000 "
b111000 (
#67000
1#
#68000
0#
b100011 "
b100011 (
#69000
1#
#70000
0#
b1011110 "
b1011110 (
#71000
b1 *
1#
#72000
0#
b110010 "
b110010 (
#73000
b1 +
1#
#74000
0#
b110100 "
b110100 (
#75000
b10 +
1#
#76000
0#
b110010 "
b110010 (
#77000
b11 +
1#
#78000
0#
b1000000 "
b1000000 (
#79000
b0 +
b10 *
1#
#80000
0#
b110000 "
b110000 (
#81000
b1 -
1#
#82000
0#
#83000
b10 -
1#
#84000
0#
#85000
b11 -
1#
#86000
0#
#87000
b100 -
1#
#88000
0#
b110011 "
b110011 (
#89000
b101 -
1#
#90000
0#
b110000 "
b110000 (
#91000
b110 -
1#
#92000
0#
b1100110 "
b1100110 (
#93000
b111 -
1#
#94000
0#
b110100 "
b110100 (
#95000
b1000 -
1#
#96000
0#
b111010 "
b111010 (
#97000
b11 *
b0 -
1#
#98000
0#
b100000 "
b100000 (
#99000
1#
#100000
0#
b100100 "
b100100 (
#101000
b100 *
b0 ,
1#
#102000
0#
b110011 "
b110011 (
#103000
b1 +
1#
#104000
0#
b110001 "
b110001 (
#105000
b10 +
1#
#106000
0#
b100000 "
b100000 (
#107000
b1 .
1#
#108000
0#
b111100 "
b111100 (
#109000
b101 *
b0 .
b0 +
1#
#110000
0#
b111101 "
b111101 (
#111000
b110 *
1#
#112000
0#
b110001 "
b110001 (
#113000
b1 -
1#
#114000
0#
b110010 "
b110010 (
#115000
b10 -
1#
#116000
0#
b110011 "
b110011 (
#117000
b11 -
1#
#118000
0#
b110010 "
b110010 (
#119000
b100 -
1#
#120000
0#
b110001 "
b110001 (
#121000
b101 -
1#
#122000
0#
b110101 "
b110101 (
#123000
b110 -
1#
#124000
0#
b100011 "
b100011 (
#125000
b0 -
b0 *
1#
#126000
0#
b1011110 "
b1011110 (
#127000
b1 *
1#
#128000
0#
b110010 "
b110010 (
#129000
b1 +
1#
#130000
0#
b110100 "
b110100 (
#131000
b10 +
1#
#132000
0#
b110010 "
b110010 (
#133000
b11 +
1#
#134000
0#
b1000000 "
b1000000 (
#135000
b0 +
b10 *
1#
#136000
0#
b110000 "
b110000 (
#137000
b1 -
1#
#138000
0#
#139000
b10 -
1#
#140000
0#
#141000
b11 -
1#
#142000
0#
#143000
b100 -
1#
#144000
0#
b110011 "
b110011 (
#145000
b101 -
1#
#146000
0#
b110000 "
b110000 (
#147000
b110 -
1#
#148000
0#
b1100110 "
b1100110 (
#149000
b111 -
1#
#150000
0#
b110100 "
b110100 (
#151000
b1000 -
1#
#152000
0#
b111010 "
b111010 (
#153000
b11 *
b0 -
1#
#154000
0#
b100000 "
b100000 (
#155000
1#
#156000
0#
b100100 "
b100100 (
#157000
b100 *
1#
#158000
0#
b110011 "
b110011 (
#159000
b1 +
1#
#160000
0#
b110001 "
b110001 (
#161000
b10 +
1#
#162000
0#
b100000 "
b100000 (
#163000
b1 .
1#
#164000
0#
b111100 "
b111100 (
#165000
b101 *
b0 .
b0 +
1#
#166000
0#
b111101 "
b111101 (
#167000
b110 *
1#
#168000
0#
b110001 "
b110001 (
#169000
b1 -
1#
#170000
0#
b110010 "
b110010 (
#171000
b10 -
1#
#172000
0#
b110011 "
b110011 (
#173000
b11 -
1#
#174000
0#
b110010 "
b110010 (
#175000
b100 -
1#
#176000
0#
b110001 "
b110001 (
#177000
b101 -
1#
#178000
0#
b110101 "
b110101 (
#179000
b110 -
1#
#180000
0#
b111000 "
b111000 (
#181000
b111 -
1#
#182000
0#
b111001 "
b111001 (
#183000
b1000 -
1#
#184000
0#
#185000
b0 *
b0 -
1#
#186000
0#
b111000 "
b111000 (
#187000
1#
#188000
0#
b100011 "
b100011 (
#189000
1#
#190000
0#
b1011110 "
b1011110 (
#191000
b1 *
1#
#192000
0#
b110010 "
b110010 (
#193000
b1 +
1#
#194000
0#
b110100 "
b110100 (
#195000
b10 +
1#
#196000
0#
b110010 "
b110010 (
#197000
b11 +
1#
#198000
0#
b1000000 "
b1000000 (
#199000
b0 +
b10 *
1#
#200000
0#
b110000 "
b110000 (
#201000
b1 -
1#
#202000
0#
#203000
b10 -
1#
#204000
0#
#205000
b11 -
1#
#206000
0#
#207000
b100 -
1#
#208000
0#
b110011 "
b110011 (
#209000
b101 -
1#
#210000
0#
b110000 "
b110000 (
#211000
b110 -
1#
#212000
0#
b1100110 "
b1100110 (
#213000
b111 -
1#
#214000
0#
b110100 "
b110100 (
#215000
b1000 -
1#
#216000
0#
b111010 "
b111010 (
#217000
b11 *
b0 -
1#
#218000
0#
b100000 "
b100000 (
#219000
1#
#220000
0#
b100100 "
b100100 (
#221000
b100 *
1#
#222000
0#
b110011 "
b110011 (
#223000
b1 +
1#
#224000
0#
b110001 "
b110001 (
#225000
b10 +
1#
#226000
0#
b100000 "
b100000 (
#227000
b1 .
1#
#228000
0#
b111100 "
b111100 (
#229000
b101 *
b0 .
b0 +
1#
#230000
0#
b111101 "
b111101 (
#231000
b110 *
1#
#232000
0#
b100011 "
b100011 (
#233000
b0 *
1#
#234000
0#
b1011110 "
b1011110 (
#235000
b1 *
1#
#236000
0#
b110010 "
b110010 (
#237000
b1 +
1#
#238000
0#
b110100 "
b110100 (
#239000
b10 +
1#
#240000
0#
b110010 "
b110010 (
#241000
b11 +
1#
#242000
0#
b1000000 "
b1000000 (
#243000
b0 +
b10 *
1#
#244000
0#
b110000 "
b110000 (
#245000
b1 -
1#
#246000
0#
#247000
b10 -
1#
#248000
0#
#249000
b11 -
1#
#250000
0#
#251000
b100 -
1#
#252000
0#
b110011 "
b110011 (
#253000
b101 -
1#
#254000
0#
b110000 "
b110000 (
#255000
b110 -
1#
#256000
0#
b1100110 "
b1100110 (
#257000
b111 -
1#
#258000
0#
b110100 "
b110100 (
#259000
b1000 -
1#
#260000
0#
b111010 "
b111010 (
#261000
b11 *
b0 -
1#
#262000
0#
b100000 "
b100000 (
#263000
1#
#264000
0#
b100100 "
b100100 (
#265000
b100 *
1#
#266000
0#
b110011 "
b110011 (
#267000
b1 +
1#
#268000
0#
b110001 "
b110001 (
#269000
b10 +
1#
#270000
0#
b100000 "
b100000 (
#271000
b1 .
1#
#272000
0#
b111100 "
b111100 (
#273000
b101 *
b0 .
b0 +
1#
#274000
0#
b111101 "
b111101 (
#275000
b110 *
1#
#276000
0#
b100000 "
b100000 (
#277000
b1 .
1#
#278000
0#
#279000
b10 .
1#
#280000
0#
#281000
b11 .
1#
#282000
0#
b110001 "
b110001 (
#283000
b1 -
1#
#284000
0#
b110010 "
b110010 (
#285000
b10 -
1#
#286000
0#
b110011 "
b110011 (
#287000
b11 -
1#
#288000
0#
b110010 "
b110010 (
#289000
b100 -
1#
#290000
0#
b110001 "
b110001 (
#291000
b101 -
1#
#292000
0#
b110101 "
b110101 (
#293000
b110 -
1#
#294000
0#
b100000 "
b100000 (
#295000
b0 .
b0 -
b0 *
1#
#296000
0#
b100011 "
b100011 (
#297000
1#
#298000
0#
b1011110 "
b1011110 (
#299000
b1 *
1#
#300000
0#
b110010 "
b110010 (
#301000
b1 +
1#
#302000
0#
b110100 "
b110100 (
#303000
b10 +
1#
#304000
0#
b110010 "
b110010 (
#305000
b11 +
1#
#306000
0#
b1000000 "
b1000000 (
#307000
b0 +
b10 *
1#
#308000
0#
b110000 "
b110000 (
#309000
b1 -
1#
#310000
0#
#311000
b10 -
1#
#312000
0#
#313000
b11 -
1#
#314000
0#
#315000
b100 -
1#
#316000
0#
b110011 "
b110011 (
#317000
b101 -
1#
#318000
0#
b110000 "
b110000 (
#319000
b110 -
1#
#320000
0#
b1100110 "
b1100110 (
#321000
b111 -
1#
#322000
0#
b110100 "
b110100 (
#323000
b1000 -
1#
#324000
0#
b111010 "
b111010 (
#325000
b11 *
b0 -
1#
#326000
0#
b100000 "
b100000 (
#327000
1#
#328000
0#
b100100 "
b100100 (
#329000
b100 *
1#
#330000
0#
b110011 "
b110011 (
#331000
b1 +
1#
#332000
0#
b110001 "
b110001 (
#333000
b10 +
1#
#334000
0#
b100000 "
b100000 (
#335000
b1 .
1#
#336000
0#
b111100 "
b111100 (
#337000
b101 *
b0 .
b0 +
1#
#338000
0#
b111101 "
b111101 (
#339000
b110 *
1#
#340000
0#
b100000 "
b100000 (
#341000
b1 .
1#
#342000
0#
#343000
b10 .
1#
#344000
0#
#345000
b11 .
1#
#346000
0#
b1100001 "
b1100001 (
#347000
b1 -
1#
#348000
0#
b1100010 "
b1100010 (
#349000
b10 -
1#
#350000
0#
b110001 "
b110001 (
#351000
b11 -
1#
#352000
0#
b110010 "
b110010 (
#353000
b100 -
1#
#354000
0#
b110011 "
b110011 (
#355000
b101 -
1#
#356000
0#
b110010 "
b110010 (
#357000
b110 -
1#
#358000
0#
b110001 "
b110001 (
#359000
b111 -
1#
#360000
0#
b110101 "
b110101 (
#361000
b1000 -
1#
#362000
0#
b100000 "
b100000 (
#363000
b0 .
b0 -
b0 *
1#
#364000
0#
b100011 "
b100011 (
#365000
1#
#366000
0#
b1011110 "
b1011110 (
#367000
b1 *
1#
#368000
0#
b110010 "
b110010 (
#369000
b1 +
1#
#370000
0#
b110100 "
b110100 (
#371000
b10 +
1#
#372000
0#
b110010 "
b110010 (
#373000
b11 +
1#
#374000
0#
b1000000 "
b1000000 (
#375000
b0 +
b10 *
1#
#376000
0#
b110000 "
b110000 (
#377000
b1 -
1#
#378000
0#
#379000
b10 -
1#
#380000
0#
#381000
b11 -
1#
#382000
0#
#383000
b100 -
1#
#384000
0#
b110011 "
b110011 (
#385000
b101 -
1#
#386000
0#
b110000 "
b110000 (
#387000
b110 -
1#
#388000
0#
b1100110 "
b1100110 (
#389000
b111 -
1#
#390000
0#
b110100 "
b110100 (
#391000
b1000 -
1#
#392000
0#
b111010 "
b111010 (
#393000
b11 *
b0 -
1#
#394000
0#
b100000 "
b100000 (
#395000
1#
#396000
0#
b100100 "
b100100 (
#397000
b100 *
1#
#398000
0#
b110011 "
b110011 (
#399000
b1 +
1#
#400000
0#
b110001 "
b110001 (
#401000
b10 +
1#
#402000
0#
b100000 "
b100000 (
#403000
b1 .
1#
#404000
0#
b111100 "
b111100 (
#405000
b101 *
b0 .
b0 +
1#
#406000
0#
b111101 "
b111101 (
#407000
b110 *
1#
#408000
0#
b100000 "
b100000 (
#409000
b1 .
1#
#410000
0#
#411000
b10 .
1#
#412000
0#
#413000
b11 .
1#
#414000
0#
b1000001 "
b1000001 (
#415000
b0 .
b0 *
1#
#416000
0#
b1100010 "
b1100010 (
#417000
1#
#418000
0#
b110001 "
b110001 (
#419000
1#
#420000
0#
b110010 "
b110010 (
#421000
1#
#422000
0#
b110011 "
b110011 (
#423000
1#
#424000
0#
b110010 "
b110010 (
#425000
1#
#426000
0#
b110001 "
b110001 (
#427000
1#
#428000
0#
b110101 "
b110101 (
#429000
1#
#430000
0#
b100000 "
b100000 (
#431000
1#
#432000
0#
b100011 "
b100011 (
#433000
1#
#434000
0#
b1011110 "
b1011110 (
#435000
b1 *
1#
#436000
0#
b110011 "
b110011 (
#437000
b1 +
1#
#438000
0#
#439000
b10 +
1#
#440000
0#
b111000 "
b111000 (
#441000
b11 +
1#
#442000
0#
b1000000 "
b1000000 (
#443000
b0 +
b10 *
1#
#444000
0#
b110000 "
b110000 (
#445000
b1 -
1#
#446000
0#
#447000
b10 -
1#
#448000
0#
#449000
b11 -
1#
#450000
0#
#451000
b100 -
1#
#452000
0#
b110011 "
b110011 (
#453000
b101 -
1#
#454000
0#
b110001 "
b110001 (
#455000
b110 -
1#
#456000
0#
b110011 "
b110011 (
#457000
b111 -
1#
#458000
0#
b110000 "
b110000 (
#459000
b1000 -
1#
#460000
0#
b111010 "
b111010 (
#461000
b11 *
b0 -
1#
#462000
0#
b100000 "
b100000 (
#463000
1#
#464000
0#
b101010 "
b101010 (
#465000
b100 *
b1 ,
1#
#466000
0#
b110000 "
b110000 (
#467000
b1 -
1#
#468000
0#
#469000
b10 -
1#
#470000
0#
#471000
b11 -
1#
#472000
0#
#473000
b100 -
1#
#474000
0#
#475000
b101 -
1#
#476000
0#
#477000
b110 -
1#
#478000
0#
b111000 "
b111000 (
#479000
b111 -
1#
