Pre/ISE-verilog/cpu_checker-Pro/cpu_checker.v
`define S0 4'd0
`define S1 4'd1
`define S2 4'd2
`define S3 4'd3
`define S4 4'd4
`define S5 4'd5
`define S6 4'd6
`define S7 4'd7
`define S8 4'd8
`define S9 4'd9
`define S10 4'd10
`define S11 4'd11

module cpu_checker(
    input clk,
    input reset,
    input [15:0] freq,
    input [7:0] char,
    output [1:0] format_type,
    output reg [3:0] error_code
  );
  reg [3:0] state;
  reg [15:0] time1,tmp1;
  reg [31:0] pc,tmp2;
  reg [31:0] addr;
  reg [15:0] grf;
  reg sw1,sw2,sw3,sw4;
  integer dexcnt=0;//十进制数字计数
  integer hexcnt=0;//16进制计数
  integer spacecnt=0;
  integer flag;//用来标记是哪一种，0是寄存器信息，1是数据存储器信息
  initial
  begin
    state=`S0;
    time1=0;
    pc=0;
    addr=0;
    grf=0;
    sw1=0;
    sw2=0;
    sw3=0;
    sw4=0;
    tmp2=0;
  end
  always @(posedge clk)
  begin
    tmp1=freq;
    tmp2=0;
    if(reset==1)
    begin
      state=`S0;
      spacecnt=0;
      hexcnt=0;
      dexcnt=0;
      time1=0;
      pc=0;
      addr=0;
      grf=0;
      sw1=0;
      sw2=0;
      sw3=0;
      sw4=0;
      error_code=4'b0;
      tmp1=0;
    end
    else
    begin
      error_code=4'b0;
      case(state)
        `S0:
        begin//^
          if(char=="^")//^
            state=`S1;
            time1=0;
            pc=0;
            addr=0;
            grf=0;
        end
        `S1:
        begin//^XXXX
          if(char>=8'd48&&char<=8'd57)
          begin
            time1=(time1<<3)+(time1<<1);
            time1=time1+char-"0";
            dexcnt=dexcnt+1;
            if(dexcnt>4)
            begin
              state=`S0;
              dexcnt=0;
              time1=0;
            end
          end
          else if(char=="@")
          begin
            if(dexcnt>=1&&dexcnt<=4)
            begin
              state=`S2;
              dexcnt=0;
            end
            else begin
              state=`S0;
              dexcnt=0;
              time1=0;              
            end
          end
          else if(char==8'd94)
          begin
            dexcnt=0;
            state=`S1;
            time1=0;
          end
          else
          begin
            state=`S0;
            dexcnt=0;
            time1=0;
          end
        end
        `S2:
        begin//^xxxx@
          if (char>=8'd48&&char<=8'd57||char>=8'd97&&char<=8'd102)
          begin
            pc=pc<<4;
            if(char>=8'd48&&char<=8'd57)
              pc=pc+char-"0";
            else begin
              pc=pc+char-"a"+10;              
            end
              
            hexcnt=hexcnt+1;
            if(hexcnt>8)
            begin
              hexcnt=0;
              state=`S0;
              pc=0;
            end
          end
          else if(char==":")
          begin
            if(hexcnt==8)
            begin
              hexcnt=0;
              state=`S3;
            end
            else
            begin
              hexcnt=0;
              state=`S0;
              pc=0;
            end
          end
          else if(char=="^")
          begin
            hexcnt=0;
            state=`S1;
            pc=0;
          end
           else begin
             hexcnt=0;
             state=`S0;
             pc=0;
           end
        end
        `S3:
        begin//^xxxx@xxxxxxxx:
          if(char=="$"||char==8'd42)
          begin
            if(char=="$")
              flag=0;
            else
              flag=1;
            state=`S4;
            grf=0;
            addr=0;
          end
          else if(char==" ")
            state=`S3;
          else if(char=="^")
            state=`S1;
          else
          begin
            state=`S0;
          end
        end
        `S4:
        begin//^xxxx@xxxxxxxx:$(8'd42)
          if(flag==0)
          begin
            if(char>=8'd48&&char<=8'd57&&spacecnt==0)
            begin
              grf=(grf<<3)+(grf<<1);
              grf=grf+char-"0";
              dexcnt=dexcnt+1;
              if(dexcnt>4)
              begin
                state=`S0;
                dexcnt=0;
                grf=0;
              end
            end
            else if(char==" ")
            begin
              if(dexcnt>=1&&dexcnt<=4)
              begin
                spacecnt=spacecnt+1;
                state=`S4;
              end
              else
              begin
                spacecnt=0;
                dexcnt=0;
                state=`S0;
                grf=0;
              end
            end
            else if(char=="<"&&dexcnt>=1&&dexcnt<=4)
            begin
              dexcnt=0;
              spacecnt=0;
              state=`S5;
            end
            else if(char=="^")
            begin
              dexcnt=0;
              spacecnt=0;
              state=`S1;
              grf=0;
            end
            else
            begin
              dexcnt=0;
              spacecnt=0;
              state=`S0;
              grf=0;
            end
          end
          else
          begin
            if((char>=8'd48&&char<=8'd57||char>=8'd97&&char<=8'd102)&&spacecnt==0)
            begin
                addr=addr<<4;
              if(char>=8'd48&&char<=8'd57)
                addr=addr+char-"0";
                else
                addr=addr+char-"a"+10;
                
              hexcnt=hexcnt+1;
              if (hexcnt>8)
              begin
                hexcnt=0;
                spacecnt=0;
                state=`S0;
                addr=0;
              end
            end
            else if(hexcnt==8&&char==" ")
            begin
              spacecnt=spacecnt+1;
              state=`S4;
            end
            else if(hexcnt==8&&char=="<")
            begin
              state=`S5;
              spacecnt=0;
              hexcnt=0;
            end
            else if(char=="^")
            begin
              spacecnt=0;
              hexcnt=0;
              state=`S1;
              addr=0;
            end
            else
            begin
              spacecnt=0;
              hexcnt=0;
              state=`S0;
              addr=0;
            end
          end
        end
        `S5:
        begin////^xxxx@xxxxxxxx:$(8'd42)xxx<=
          if(char=="=")
          begin
            state=`S6;
          end
          else if(char=="^")
          begin
            state=`S1;
          end
          else
            state=`S0;
        end
        `S6:
        begin
          if(char==" "&&hexcnt==0)
          begin
            spacecnt=spacecnt+1;
            state=`S6;
          end
          else if(char>=8'd48&&char<=8'd57||char>=8'd97&&char<=8'd102)
          begin
            hexcnt=hexcnt+1;
            if (hexcnt>8)
            begin
              hexcnt=0;
              spacecnt=0;
              state=`S0;
            end
          end
          else if(char=="#")
          begin
            if(hexcnt==8)
            begin
              state=`S7;
              hexcnt=0;
              spacecnt=0;
              if(state==`S7)begin
        tmp1=tmp1>>1;
        tmp2=16'b0;
        while(time1>tmp2)begin
            tmp2=tmp2+tmp1;
        end
        if(time1==tmp2)
         error_code[0]=0;
          else
         error_code[0]=1; 
        if((pc&32'd3)==32'h0 && pc>=32'h00003000 && pc<=32'h00004fff)
          error_code[1]=0;
        else
          error_code[1]=1;
      if(flag==1) begin
      if((addr&32'd3)==32'h0 && (addr>=32'h00000000 && addr<=32'h00002fff))
          error_code[2]=0;
       else
          error_code[2]=1;
      end
      if(flag==0)begin
      if(grf>=16'd0&&grf<=16'd31)
          error_code[3]=0;
      else
          error_code[3]=1;
      end
      end    
            end
            else
            begin
              state=`S0;
              hexcnt=0;
              spacecnt=0;
            end
          end
          else if(char=="^")
          begin
            state=`S1;
            hexcnt=0;
            spacecnt=0;
          end
          else
          begin
            state=`S0;
            hexcnt=0;
            spacecnt=0;
          end
        end
        `S7:
        begin
          if(char=="^")
            state=`S1;
          else 
            state=`S0;
            time1=0;
            pc=0;
            addr=0;
            grf=0;
        end
      endcase
    end
  end
  assign format_type=(state==`S7&&flag==0)?2'b01:(state==`S7&&flag==1)?2'b10:2'b00;
  //assign error_code=(state==`S7)?{sw4,sw3,sw2,sw1}:4'b0;
endmodule

Pre/ISE-verilog/cpu_checker-Pro/tb.v
`timescale  1ns / 1ps
`include "cpu_checker.v"
module tb_cpu_checker;

// cpu_checker Parameters


// cpu_checker Inputs
reg   clk                                  = 0 ;
reg   reset                                = 0 ;
reg   [15:0]  freq                         = 0 ;
reg   [7:0]  char                          = 0 ;

// cpu_checker Outputs
wire  [1:0]  format_type                   ;
wire  [3:0]  error_code                    ;


cpu_checker  u_cpu_checker (
    .clk                     ( clk                 ),
    .reset                   ( reset               ),
    .freq                    ( freq         [15:0] ),
    .char                    ( char         [7:0]  ),

    .format_type             ( format_type  [1:0]  ),
    .error_code              ( error_code   [3:0]  )
);

initial
begin
    $dumpfile("cpu_checker_wave.vcd");
		$dumpvars;
		clk = 0;
		reset = 1;
		char = 0;
		freq = 16'd4;
		#10 reset = 0;
#2 char = "^";
#2 char = "3";
#2 char = "2";
#2 char = "@";
#2 char = "0";
#2 char = "0";
#2 char = "0";
#2 char = "0";
#2 char = "3";
#2 char = "0";
#2 char = "0";
#2 char = "4";
#2 char = ":";
#2 char = " ";
#2 char = "$";
#2 char = "0";
#2 char = "0";
#2 char = "4";
#2 char = "0";
#2 char = "<";
#2 char = "=";
#2 char = "1";
#2 char = "2";
#2 char = "3";
#2 char = "4";
#2 char = "5";
#2 char = "6";
#2 char = "7";
#2 char = "8";
#2 char = "#";
#2 char=  " ";
#2 char=  " ";
#2 char=  " ";
#20
		$finish;
    $finish;
end
    always #1 clk = ~clk;
endmodule

Pre/ISE-verilog/cpu_checker-Pro/cpu_checker_wave.vcd
$date
	Mon Aug 29 20:57:31 2022
$end
$version
	Icarus Verilog
$end
$timescale
	1ps
$end
$scope module tb_cpu_checker $end
$var wire 2 ! format_type [1:0] $end
$var wire 4 " error_code [3:0] $end
$var reg 8 # char [7:0] $end
$var reg 1 $ clk $end
$var reg 16 % freq [15:0] $end
$var reg 1 & reset $end
$scope module u_cpu_checker $end
$var wire 8 ' char [7:0] $end
$var wire 1 $ clk $end
$var wire 16 ( freq [15:0] $end
$var wire 1 & reset $end
$var wire 2 ) format_type [1:0] $end
$var reg 32 * addr [31:0] $end
$var reg 4 + error_code [3:0] $end
$var reg 16 , grf [15:0] $end
$var reg 32 - pc [31:0] $end
$var reg 4 . state [3:0] $end
$var reg 1 / sw1 $end
$var reg 1 0 sw2 $end
$var reg 1 1 sw3 $end
$var reg 1 2 sw4 $end
$var reg 16 3 time1 [15:0] $end
$var reg 16 4 tmp1 [15:0] $end
$var reg 32 5 tmp2 [31:0] $end
$var integer 32 6 dexcnt [31:0] $end
$var integer 32 7 flag [31:0] $end
$var integer 32 8 hexcnt [31:0] $end
$var integer 32 9 spacecnt [31:0] $end
$upscope $end
$upscope $end
$enddefinitions $end
#0
$dumpvars
b0 9
b0 8
bx 7
b0 6
b0 5
bx 4
b0 3
02
01
00
0/
b0 .
b0 -
b0 ,
bx +
b0 *
b0 )
b100 (
b0 '
1&
b100 %
0$
b0 #
bx "
b0 !
$end
#1000
b0 "
b0 +
b0 4
1$
#2000
0$
#3000
b0 4
1$
#4000
0$
#5000
b0 4
1$
#6000
0$
#7000
b0 4
1$
#8000
0$
#9000
b0 4
1$
#10000
0$
0&
#11000
b100 4
1$
#12000
0$
b1011110 #
b1011110 '
#13000
b1 .
1$
#14000
0$
b110011 #
b110011 '
#15000
b1 6
b11 3
1$
#16000
0$
b110010 #
b110010 '
#17000
b10 6
b100000 3
1$
#18000
0$
b1000000 #
b1000000 '
#19000
b0 6
b10 .
1$
#20000
0$
b110000 #
b110000 '
#21000
b1 8
1$
#22000
0$
#23000
b10 8
1$
#24000
0$
#25000
b11 8
1$
#26000
0$
#27000
b100 8
1$
#28000
0$
b110011 #
b110011 '
#29000
b101 8
b11 -
1$
#30000
0$
b110000 #
b110000 '
#31000
b110 8
b110000 -
1$
#32000
0$
#33000
b111 8
b1100000000 -
1$
#34000
0$
b110100 #
b110100 '
#35000
b1000 8
b11000000000100 -
1$
#36000
0$
b111010 #
b111010 '
#37000
b11 .
b0 8
1$
#38000
0$
b100000 #
b100000 '
#39000
1$
#40000
0$
b100100 #
b100100 '
#41000
b100 .
b0 7
1$
#42000
0$
b110000 #
b110000 '
#43000
b1 6
1$
#44000
0$
#45000
b10 6
1$
#46000
0$
b110100 #
b110100 '
#47000
b11 6
b100 ,
1$
#48000
0$
b110000 #
b110000 '
#49000
b100 6
b101000 ,
1$
#50000
0$
b111100 #
b111100 '
#51000
b101 .
b0 6
1$
#52000
0$
b111101 #
b111101 '
#53000
b110 .
1$
#54000
0$
b110001 #
b110001 '
#55000
b1 8
1$
#56000
0$
b110010 #
b110010 '
#57000
b10 8
1$
#58000
0$
b110011 #
b110011 '
#59000
b11 8
1$
#60000
0$
b110100 #
b110100 '
#61000
b100 8
1$
#62000
0$
b110101 #
b110101 '
#63000
b101 8
1$
#64000
0$
b110110 #
b110110 '
#65000
b110 8
1$
#66000
0$
b110111 #
b110111 '
#67000
b111 8
1$
#68000
0$
b111000 #
b111000 '
#69000
b1000 8
1$
#70000
0$
b100011 #
b100011 '
#71000
b1 !
b1 )
b1000 "
b1000 +
b100000 5
b10 4
b0 8
b111 .
1$
#72000
0$
b100000 #
b100000 '
#73000
b0 !
b0 )
b0 ,
b0 -
b0 3
b0 .
b0 "
b0 +
b0 5
b100 4
1$
